gym_shopping_cart/__init__.py
gym_shopping_cart/data/__init__.py
gym_shopping_cart/data/parser.py
gym_shopping_cart/data/test_data.tar.gz
gym_shopping_cart/envs/__init__.py
gym_shopping_cart/envs/shopping_cart_v0.py
tests/__init__.py
tests/generate_test_data.py
tests/test_processed_instacart_data.py
tests/test_shopping_cart_v0.py
tests/test_simple_shopping_cart_v0.py
gym_shopping_cart-0.2.0.dist-info/LICENSE
gym_shopping_cart-0.2.0.dist-info/METADATA
gym_shopping_cart-0.2.0.dist-info/WHEEL
gym_shopping_cart-0.2.0.dist-info/top_level.txt
gym_shopping_cart-0.2.0.dist-info/RECORD
