Metadata-Version: 2.1
Name: gym-shopping-cart
Version: 0.2.0
Summary: An OpenAI Gym for Shopping Cart Reinforcement Learning
Home-page: https://gitlab.com/winderresearch/gym-shopping-cart
Author: Phil Winder
Author-email: phil@winderresearch.com
License: MIT
Platform: UNKNOWN
Requires-Dist: gym (>=0.12.5)
Requires-Dist: pandas (>=0.18.1)
